{
  "data": [
    {
      "index": 0,
      "name": "Menü ",
      "path": "menu-3",
      "local": "header",
      "category": "menu",
      "desing": {
        "logo": "logo.svg",
        "logosize": 300,
        "logosizemobil": 200,
        "color": "#000"
      },
      "id": "ebbpbt",
      "version": "1.0.0",
      "icon": "menu",
      "data": [
        {
          "name": {
            "tr": "Bizi hemen arayın"
          },
          "spot": "0342 341 41 31",
          "icon": "phone",
          "externalUrl": "",
          "titlecolor": "#000",
          "spotcolor": "#000",
          "iconcolor": "#000"
        },
        {
          "name": {
            "tr": "Bize yazın"
          },
          "spot": "info@{{domain}}",
          "icon": "mail",
          "url": "info@{{domain}}",
          "titlecolor": "#000",
          "spotcolor": "#000",
          "iconcolor": "#000"
        },
        {
          "name": {
            "tr": "BATIKENT MH 9132 NOLU SK NO: 5/D"
          },
          "spot": "ŞEHİTKAMİL / GAZİANTEP",
          "icon": "location_on",
          "externalUrl": "",
          "titlecolor": "#000",
          "spotcolor": "#000",
          "iconcolor": "#000"
        }
      ]
    },
    {
      "index": 1,
      "name": "Footer 1",
      "path": "footer-1",
      "local": "footer",
      "category": "footer",
      "desing": {
        "bgcolor": "#85260f",
        "color": "#fff",
        "img": "",
        "imgwidth": "250px"
      },
      "data": [],
      "id": "a1b1uf",
      "version": "1.0.0",
      "icon": "web_asset"
    },
    {
      "index": 2,
      "name": "Slider",
      "path": "slider",
      "local": "header",
      "category": "slider",
      "desing": {
        "delay": 3000
      },
      "data": [
        {
          "img": "1.jpg"
        },
        {
          "img": "2.jpg"
        },
        {
          "img": "3.jpg"
        }
      ],
      "id": "mfzpnk",
      "version": "1.0.0",
      "icon": "view_carousel"
    },
    {
      "index": 3,
      "name": "Tanıtım Modülü",
      "path": "module-1",
      "local": "body",
      "category": "module",
      "desing": {
        "name": {
          "tr": "SAİB'i Tanıyın",
          "en": "",
          "ar": ""
        },
        "spot": {
          "tr": "SAİB, Suriye ve Türkiye'deki iş insanlarını bir araya getirerek ticari faaliyetleri kolaylaştırmak, yeni ticari alanlar oluşturmak, kamu yararına projeler yürütmek ve ekonomik kalkınmaya destek sağlamak amacıyla Gaziantep'te kurulmuş uluslararası bir sivil toplum kuruluşudur.",
          "en": "",
          "ar": ""
        },
        "name2": {
          "tr": "Vizyonumuz",
          "en": "",
          "ar": ""
        },
        "spot2": {
          "tr": "Türkiye ve Suriye arasında kalıcı ticari köprüler kurarak, uluslararası pazarlarda güçlü bir ekonomik iş birliği ağı oluşturmak.",
          "en": "",
          "ar": ""
        },
        "icon2": "home",
        "name3": {
          "tr": "Misyonumuz",
          "en": "",
          "ar": ""
        },
        "spot3": {
          "tr": "Üretim, yatırım ve ihracat potansiyelini artırmak; sanayici, bilim insanı ve iş insanlarını ortak bir teşkilatta birleştirip, bölgesel kalkınmayı hızlandırmak.",
          "en": "",
          "ar": ""
        },
        "icon3": "home",
        "img": "profil.webp",
        "bgcolor": "#85260f",
        "fontcolor": "#fff",
        "margintop": "20",
        "marginbotton": "20"
      },
      "id": "sykhyk",
      "version": "1.0.0",
      "icon": "business"
    },
    {
      "index": 4,
      "name": "Page Slider",
      "path": "page-slider",
      "local": "body",
      "category": "page slider",
      "desing": {
        "page": "altsayfalar",
        "name": {
          "tr": "Saib Uluslararası Suriyeli İş Adamları Derneği",
          "en": "",
          "ar": ""
        },
        "color": "#0455d8",
        "aspect-ratio": "2/1",
        "delay": "3000"
      },
      "id": "zs4epo",
      "version": "1.0.0",
      "icon": "view_carousel"
    },
    {
      "index": 5,
      "name": "Page Desing 5",
      "path": "page-desing-5",
      "local": "body",
      "category": "page",
      "desing": {
        "height": "100",
        "opacity": "0.5",
        "font-size": "32",
        "backgroundcolor": "#85260f",
        "menu-active": "#85260f"
      },
      "id": "onx8x4",
      "version": "1.0.0",
      "icon": "web"
    },
    {
      "index": 6,
      "name": "Maps",
      "path": "map",
      "local": "body",
      "category": "map",
      "desing": {
        "height": "200",
        "opacity": "0.5",
        "backgroundcolor": "#000",
        "color": "#1e3046",
        "img": "map.jpg",
        "externalUrl": "https://www.google.com/maps/place/37%C2%B004'20.4%22N+37%C2%B019'45.7%22E/@37.072343,37.3259215,17z/data=!3m1!4b1!4m7!1m2!2m1!1zQkFUSUtFTlQgTUggOTEzMiBOT0xVIFNLIE5POiA1L0QgxZ5FSMSwVEtBTcSwTCAvIEdBWsSwQU5URVA!3m3!8m2!3d37.07234!4d37.329362?entry=ttu&g_ep=EgoyMDI1MTAwOC4wIKXMDSoASAFQAw%3D%3D"
      },
      "id": "mct10p",
      "version": "1.0.0",
      "icon": "map"
    },
    {
      "name": "İletişim",
      "path": "contact-3",
      "local": "body",
      "category": "contact",
      "desing": {
        "color": "#1e3046",
        "name": {
          "tr": "Bize Ulaşın",
          "en": "",
          "ar": ""
        },
        "margin": "30px 0px 30px 0px"
      },
      "data": [
        {
          "icon": "phone",
          "text": "0342 341 41 31",
          "url": "tel:03423414131"
        },
        {
          "icon": "email",
          "text": "info@{{domain}}"
        },
        {
          "icon": "map",
          "text": "BATIKENT MH 9132 NOLU SK NO: 5/D ŞEHİTKAMİL / GAZİANTEP"
        }
      ],
      "id": "xny5up",
      "index": 7,
      "version": "1.0.0",
      "icon": "contact_mail"
    },
    {
      "index": 8,
      "name": "Haberler Liste",
      "path": "page-haber-list",
      "local": "body",
      "category": "page list",
      "id": "rx8kyl",
      "desing": {
        "name": {
          "tr": "Sayfa Listesi",
          "en": "",
          "ar": ""
        },
        "page": "haberler",
        "size": 3,
        "category": "",
        "aspect-ratio": "3 / 2",
        "margin": "0px 0px 0px 0px",
        "max": 20,
        "readMore": {
          "tr": "Haberi Oku",
          "en": "Read More",
          "ar": "اقرأ المزيد"
        }
      },
      "version": "1.0.0",
      "icon": "newsmode",
      "type": "module",
      "author": "Code Matrix",
      "data": {}
    },
    {
      "name": "Page Haber",
      "path": "page-detay-haber",
      "local": "body",
      "category": "page",
      "id": "kxp652",
      "desing": {
        "category": "page",
        "page": "page",
        "max": 6
      },
      "index": 9
    },
    {
      "index": 10,
      "name": "Üyelerimiz",
      "path": "module-slider-list",
      "local": "body",
      "category": "slider",
      "id": "nm9rmo",
      "desing": {
        "name": {
          "tr": "Üyelerimiz",
          "en": "",
          "ar": ""
        },
        "size": 6,
        "button": "true",
        "aspect-ratio": "1/1",
        "color1": "#fff",
        "color2": "#e9e9e9"
      },
      "data": [
        {
          "img": "saib.jpg"
        },
        {
          "img": "saib.jpg"
        },
        {
          "img": "saib.jpg"
        },
        {
          "img": "saib.jpg"
        },
        {
          "img": "saib.jpg"
        },
        {
          "img": "saib.jpg"
        },
        {
          "img": "saib.jpg"
        },
        {
          "img": "saib.jpg"
        },
        {
          "img": "saib.jpg"
        },
        {
          "img": "saib.jpg"
        }
      ],
      "version": "1.0.0",
      "icon": "view_carousel"
    },
    {
      "index": 11,
      "name": "Dernek Üyelik Formu",
      "path": "uyelikform",
      "local": "body",
      "category": "form",
      "id": "vd8h6j",
      "version": "1.1.0",
      "icon": "approval_delegation",
      "desing": {
        "name": {
          "tr": "Üyelik Başvuru Formu",
          "en": "Membership Application Form",
          "ar": ""
        },
        "colors": {
          "primary": "#0d2f66",
          "primaryDark": "#153b7a",
          "background": "#f2f5fb",
          "surface": "#ffffff",
          "border": "#c6d2eb",
          "accent": "#4c5d86",
          "muted": "#5b6c8f",
          "textPrimary": "#1c2c4f",
          "textSecondary": "#58698f",
          "success": "#1f8f4d",
          "error": "#d93025",
          "tr": "",
          "en": "",
          "ar": ""
        },
        "texts": {
          "organization": {
            "tr": "SAİB - Suriyeli ve Türk İş İnsanları Derneği",
            "en": "SAIB - Syrian Turkish Business Association"
          },
          "formTitle": {
            "tr": "SAİB Üyelik Başvuru Formu",
            "en": "SAIB Membership Application Form"
          },
          "formSubtitle": {
            "tr": "SAİB ağına katılmak için lütfen kişisel ve firma bilgilerinizi eksiksiz doldurunuz.",
            "en": "Please complete your personal and company details to join the SAIB network."
          },
          "formFooter": {
            "tr": "Başvurunuz SAİB yönetimi tarafından değerlendirilecek ve en kısa sürede geri dönüş yapılacaktır.",
            "en": "Your application will be reviewed by the SAIB board and we will contact you shortly."
          },
          "submit": {
            "tr": "SAİB Başvurusunu Gönder",
            "en": "Submit SAIB Application"
          },
          "submitting": {
            "tr": "Başvurunuz SAİB yönetimine iletiliyor...",
            "en": "Sending your application to the SAIB board..."
          },
          "success": {
            "tr": "SAİB üyelik başvurunuz başarıyla alındı. Ekibimiz en kısa sürede sizinle iletişime geçecek.",
            "en": "Your SAIB membership application has been received. Our team will contact you shortly."
          },
          "error": {
            "tr": "Başvurunuz iletilirken bir hata oluştu. Lütfen tekrar deneyin veya SAİB ile iletişime geçin.",
            "en": "An error occurred while submitting your application. Please try again or contact SAIB."
          },
          "loginRequired": {
            "tr": "SAİB üyelik başvurusu göndermek için giriş yapmalısınız.",
            "en": "You need to sign in to submit the SAIB membership application."
          },
          "tr": "",
          "en": "",
          "ar": ""
        },
        "firebase": {
          "collection": "membershipApplications",
          "requireAuth": false,
          "statusField": "status",
          "defaultStatus": "new",
          "tr": "",
          "en": "",
          "ar": ""
        }
      },
      "data": [
        {
          "type": "section",
          "id": "personal",
          "title": {
            "tr": "Nüfus ile İlgili Bilgiler",
            "en": "Personal Information"
          },
          "rows": [
            {
              "type": "fields",
              "columns": [
                {
                  "type": "text",
                  "name": "fullName",
                  "label": {
                    "tr": "Ad Soyad",
                    "en": "Full Name"
                  },
                  "placeholder": {
                    "tr": "Adınızı ve soyadınızı giriniz",
                    "en": "Enter your full name"
                  },
                  "required": true
                },
                {
                  "type": "text",
                  "name": "identityNumber",
                  "label": {
                    "tr": "TC Kimlik No",
                    "en": "National ID Number"
                  },
                  "placeholder": {
                    "tr": "11 haneli kimlik numarası",
                    "en": "11-digit national ID number"
                  },
                  "maxLength": 11,
                  "required": true
                }
              ]
            },
            {
              "type": "fields",
              "columns": [
                {
                  "type": "text",
                  "name": "birthDate",
                  "inputType": "date",
                  "label": {
                    "tr": "Doğum Tarihi",
                    "en": "Date of Birth"
                  },
                  "placeholder": {
                    "tr": "Gün-Ay-Yıl",
                    "en": "Day-Month-Year"
                  },
                  "required": true
                },
                {
                  "type": "text",
                  "name": "birthPlace",
                  "label": {
                    "tr": "Doğum Yeri",
                    "en": "Place of Birth"
                  },
                  "placeholder": {
                    "tr": "Şehir / Ülke",
                    "en": "City / Country"
                  },
                  "required": true
                }
              ]
            },
            {
              "type": "fields",
              "columns": [
                {
                  "type": "text",
                  "name": "registeredProvince",
                  "label": {
                    "tr": "Nüfusa Kayıtlı Olduğunuz İl",
                    "en": "Registered Province"
                  },
                  "placeholder": {
                    "tr": "İl adı",
                    "en": "Province name"
                  },
                  "required": true
                },
                {
                  "type": "text",
                  "name": "registeredDistrict",
                  "label": {
                    "tr": "İlçe",
                    "en": "District"
                  },
                  "placeholder": {
                    "tr": "İlçe adı",
                    "en": "District name"
                  },
                  "required": true
                }
              ]
            }
          ]
        },
        {
          "type": "section",
          "id": "education",
          "title": {
            "tr": "Öğrenim ile İlgili Bilgiler",
            "en": "Education Information"
          },
          "rows": [
            {
              "type": "fields",
              "columns": [
                {
                  "type": "checkbox-list",
                  "name": "educationLevels",
                  "columns": 3,
                  "label": {
                    "tr": "Öğrenim Durumu",
                    "en": "Education Level"
                  },
                  "options": [
                    {
                      "value": "primary",
                      "label": {
                        "tr": "İlkokul",
                        "en": "Primary School"
                      }
                    },
                    {
                      "value": "secondary",
                      "label": {
                        "tr": "Ortaokul",
                        "en": "Middle School"
                      }
                    },
                    {
                      "value": "highschool",
                      "label": {
                        "tr": "Lise",
                        "en": "High School"
                      }
                    },
                    {
                      "value": "bachelor",
                      "label": {
                        "tr": "Lisans",
                        "en": "Bachelor's"
                      }
                    },
                    {
                      "value": "postgraduate",
                      "label": {
                        "tr": "Lisans Üstü",
                        "en": "Postgraduate"
                      }
                    }
                  ]
                },
                {
                  "type": "text",
                  "name": "graduatedSchool",
                  "label": {
                    "tr": "Okul",
                    "en": "School"
                  },
                  "placeholder": {
                    "tr": "Mezun olduğunuz kurum",
                    "en": "Institution you graduated from"
                  }
                }
              ]
            },
            {
              "type": "fields",
              "columns": [
                {
                  "type": "text",
                  "name": "primaryForeignLanguage",
                  "label": {
                    "tr": "Yabancı Dil",
                    "en": "Foreign Language"
                  },
                  "placeholder": {
                    "tr": "Dil adı",
                    "en": "Language name"
                  }
                },
                {
                  "type": "select",
                  "name": "primaryForeignLanguageLevel",
                  "label": {
                    "tr": "Seviye",
                    "en": "Proficiency"
                  },
                  "options": [
                    {
                      "value": "intermediate",
                      "label": {
                        "tr": "Orta",
                        "en": "Intermediate"
                      }
                    },
                    {
                      "value": "good",
                      "label": {
                        "tr": "İyi",
                        "en": "Good"
                      }
                    },
                    {
                      "value": "excellent",
                      "label": {
                        "tr": "Çok İyi",
                        "en": "Excellent"
                      }
                    }
                  ]
                }
              ]
            },
            {
              "type": "fields",
              "columns": [
                {
                  "type": "text",
                  "name": "secondaryForeignLanguage",
                  "label": {
                    "tr": "İkinci Yabancı Dil",
                    "en": "Second Foreign Language"
                  },
                  "placeholder": {
                    "tr": "Dil adı",
                    "en": "Language name"
                  }
                },
                {
                  "type": "select",
                  "name": "secondaryForeignLanguageLevel",
                  "label": {
                    "tr": "Seviye",
                    "en": "Proficiency"
                  },
                  "options": [
                    {
                      "value": "intermediate",
                      "label": {
                        "tr": "Orta",
                        "en": "Intermediate"
                      }
                    },
                    {
                      "value": "good",
                      "label": {
                        "tr": "İyi",
                        "en": "Good"
                      }
                    },
                    {
                      "value": "excellent",
                      "label": {
                        "tr": "Çok İyi",
                        "en": "Excellent"
                      }
                    }
                  ]
                }
              ]
            }
          ]
        },
        {
          "type": "section",
          "id": "company",
          "title": {
            "tr": "Firmanıza Ait Bilgiler",
            "en": "Company Information"
          },
          "rows": [
            {
              "type": "fields",
              "columns": [
                {
                  "type": "text",
                  "name": "companyName",
                  "label": {
                    "tr": "Firmanızın Adı",
                    "en": "Company Name"
                  },
                  "placeholder": {
                    "tr": "Ticari unvan",
                    "en": "Registered name"
                  },
                  "required": true
                },
                {
                  "type": "text",
                  "name": "establishmentYear",
                  "inputType": "number",
                  "label": {
                    "tr": "Kuruluş Yılı",
                    "en": "Year Founded"
                  },
                  "placeholder": {
                    "tr": "YYYY",
                    "en": "YYYY"
                  }
                }
              ]
            },
            {
              "type": "fields",
              "columns": [
                {
                  "type": "subheading",
                  "label": {
                    "tr": "İletişim Bilgileri",
                    "en": "Contact Information"
                  }
                }
              ]
            },
            {
              "type": "fields",
              "columns": [
                {
                  "type": "textarea",
                  "name": "companyAddress",
                  "label": {
                    "tr": "Adres",
                    "en": "Address"
                  },
                  "placeholder": {
                    "tr": "Şirket merkez adresi",
                    "en": "Company headquarters address"
                  },
                  "rows": 3
                }
              ]
            },
            {
              "type": "fields",
              "columns": [
                {
                  "type": "text",
                  "name": "companyWebsite",
                  "inputType": "url",
                  "label": {
                    "tr": "Web Site",
                    "en": "Website"
                  },
                  "placeholder": {
                    "tr": "https://",
                    "en": "https://"
                  }
                },
                {
                  "type": "text",
                  "name": "companyPhone",
                  "label": {
                    "tr": "Cep No",
                    "en": "Mobile Phone"
                  },
                  "placeholder": {
                    "tr": "5XX XXX XX XX",
                    "en": "+90 5XX XXX XX XX"
                  }
                }
              ]
            },
            {
              "type": "fields",
              "columns": [
                {
                  "type": "checkbox-list",
                  "name": "companySectors",
                  "columns": 3,
                  "label": {
                    "tr": "Sektörünüz",
                    "en": "Business Sector"
                  },
                  "options": [
                    {
                      "value": "industry",
                      "label": {
                        "tr": "Sanayi",
                        "en": "Industry"
                      }
                    },
                    {
                      "value": "services",
                      "label": {
                        "tr": "Hizmetler",
                        "en": "Services"
                      }
                    },
                    {
                      "value": "agriculture",
                      "label": {
                        "tr": "Tarım",
                        "en": "Agriculture"
                      }
                    },
                    {
                      "value": "finance",
                      "label": {
                        "tr": "Finansal",
                        "en": "Financial"
                      }
                    },
                    {
                      "value": "contractor",
                      "label": {
                        "tr": "Yüklenici (Contractor)",
                        "en": "Contractor"
                      }
                    },
                    {
                      "value": "other",
                      "label": {
                        "tr": "Diğer",
                        "en": "Other"
                      }
                    }
                  ]
                }
              ]
            },
            {
              "type": "fields",
              "columns": [
                {
                  "type": "checkbox-list",
                  "name": "businessActivities",
                  "columns": 3,
                  "label": {
                    "tr": "Faaliyet Tipi",
                    "en": "Business Activity"
                  },
                  "options": [
                    {
                      "value": "producer",
                      "label": {
                        "tr": "Üretici",
                        "en": "Manufacturer"
                      }
                    },
                    {
                      "value": "wholesaler",
                      "label": {
                        "tr": "Toptancı",
                        "en": "Wholesaler"
                      }
                    },
                    {
                      "value": "importer",
                      "label": {
                        "tr": "İthalatçı",
                        "en": "Importer"
                      }
                    },
                    {
                      "value": "exporter",
                      "label": {
                        "tr": "İhracatçı",
                        "en": "Exporter"
                      }
                    },
                    {
                      "value": "logistics",
                      "label": {
                        "tr": "Lojistik",
                        "en": "Logistics"
                      }
                    },
                    {
                      "value": "other",
                      "label": {
                        "tr": "Diğer",
                        "en": "Other"
                      }
                    }
                  ]
                }
              ]
            },
            {
              "type": "fields",
              "columns": [
                {
                  "type": "text",
                  "name": "annualRevenue",
                  "label": {
                    "tr": "Yıllık Cirosu",
                    "en": "Annual Revenue"
                  },
                  "placeholder": {
                    "tr": "Örn: 50.000.000 ₺",
                    "en": "e.g. 50,000,000 ₺"
                  }
                },
                {
                  "type": "text",
                  "name": "employeeCount",
                  "inputType": "number",
                  "label": {
                    "tr": "Çalışan Sayısı",
                    "en": "Number of Employees"
                  },
                  "placeholder": {
                    "tr": "Örn: 45",
                    "en": "e.g. 45"
                  }
                }
              ]
            }
          ]
        },
        {
          "type": "section",
          "id": "memberships",
          "title": {
            "tr": "Halen Üye Olunan Diğer Kuruluşlar",
            "en": "Current Memberships in Other Organizations"
          },
          "subtitle": {
            "tr": "(Parti, Dernek, Vakıf, Grup, Kulüp)",
            "en": "(Party, Association, Foundation, Group, Club)"
          },
          "rows": [
            {
              "type": "line-list",
              "name": "otherMemberships",
              "count": 6,
              "label": {
                "tr": "Kuruluş / Görev",
                "en": "Organization / Role"
              },
              "placeholder": {
                "tr": "Kuruluş adı ve göreviniz",
                "en": "Organization name and your role"
              }
            }
          ]
        },
        {
          "type": "section",
          "id": "references",
          "title": {
            "tr": "Başvuru Sahibinin Üyeliği Kabul için Refer",
            "en": "References Supporting the Application"
          },
          "rows": [
            {
              "type": "line-list",
              "name": "references",
              "count": 2,
              "label": {
                "tr": "Ad Soyad",
                "en": "Full Name"
              },
              "placeholder": {
                "tr": "Referans kişisinin adı ve iletişimi",
                "en": "Reference name and contact details"
              }
            }
          ]
        }
      ]
    }
  ]
}